odoo/addons/edi_exchange_deduplicate_oca/README.rst
odoo/addons/edi_exchange_deduplicate_oca/__init__.py
odoo/addons/edi_exchange_deduplicate_oca/__manifest__.py
odoo/addons/edi_exchange_deduplicate_oca/data/cron.xml
odoo/addons/edi_exchange_deduplicate_oca/i18n/edi_exchange_deduplicate_oca.pot
odoo/addons/edi_exchange_deduplicate_oca/i18n/it.po
odoo/addons/edi_exchange_deduplicate_oca/models/__init__.py
odoo/addons/edi_exchange_deduplicate_oca/models/edi_backend.py
odoo/addons/edi_exchange_deduplicate_oca/models/edi_exchange_record.py
odoo/addons/edi_exchange_deduplicate_oca/models/edi_exchange_type.py
odoo/addons/edi_exchange_deduplicate_oca/readme/CONFIGURE.rst
odoo/addons/edi_exchange_deduplicate_oca/readme/CONTRIBUTORS.rst
odoo/addons/edi_exchange_deduplicate_oca/readme/DESCRIPTION.rst
odoo/addons/edi_exchange_deduplicate_oca/readme/USAGE.rst
odoo/addons/edi_exchange_deduplicate_oca/static/description/icon.png
odoo/addons/edi_exchange_deduplicate_oca/static/description/index.html
odoo/addons/edi_exchange_deduplicate_oca/tests/__init__.py
odoo/addons/edi_exchange_deduplicate_oca/tests/test_edi_backend_cron.py
odoo/addons/edi_exchange_deduplicate_oca/tests/test_edi_duplicate.py
odoo/addons/edi_exchange_deduplicate_oca/views/edi_exchange_type_views.xml
odoo_addon_edi_exchange_deduplicate_oca-16.0.1.1.0.2.dist-info/METADATA
odoo_addon_edi_exchange_deduplicate_oca-16.0.1.1.0.2.dist-info/WHEEL
odoo_addon_edi_exchange_deduplicate_oca-16.0.1.1.0.2.dist-info/top_level.txt
odoo_addon_edi_exchange_deduplicate_oca-16.0.1.1.0.2.dist-info/RECORD
